.gitignore
Makefile
README.md
VERSION
config.json
setup.cfg
setup.py
./LICENSE
./octomy/batch/__init__.py
./octomy/batch/cli.py
./octomy/batch/p.py
./octomy/batch/types.py
./octomy/batch/filters/__init__.py
./octomy/batch/filters/base/__init__.py
./octomy/batch/filters/base/hello.py
./octomy/batch/filters/utils/__init__.py
./octomy/batch/filters/utils/eval.py
./octomy/batch/filters/utils/ping.py
./octomy/batch/filters/utils/test.py
./octomy/batch/server/WebsiteIO.py
./octomy/batch/server/__init__.py
./octomy/batch/sql/book_batch_item.sql
./octomy/batch/sql/book_throttled_batch_item.sql
./octomy/batch/sql/bump_batch_item.sql
./octomy/batch/sql/bump_batch_item_status.sql
./octomy/batch/sql/bump_batch_items.sql
./octomy/batch/sql/create_batch_items.sql
./octomy/batch/sql/create_batch_status_enum.sql
./octomy/batch/sql/create_gcra_throttle.sql
./octomy/batch/sql/delete_all.sql
./octomy/batch/sql/delete_batch_items_with_status.sql
./octomy/batch/sql/delete_by_id.sql
./octomy/batch/sql/get_job_counts.sql
./octomy/batch/sql/get_job_times.sql
./octomy/batch/sql/get_jobs.sql
./octomy/batch/sql/get_now.sql
./octomy/batch/sql/get_status_counts.sql
./octomy/batch/sql/get_type_counts.sql
./octomy/batch/sql/get_worker_stats.sql
./octomy/batch/sql/insert_batch_item.sql
./octomy/batch/sql/update_batch_hang_status.sql
./octomy_batch.egg-info/PKG-INFO
./octomy_batch.egg-info/SOURCES.txt
./octomy_batch.egg-info/dependency_links.txt
./octomy_batch.egg-info/entry_points.txt
./octomy_batch.egg-info/namespace_packages.txt
./octomy_batch.egg-info/requires.txt
./octomy_batch.egg-info/top_level.txt
./octomy_batch.egg-info/zip-safe
.gitlab/ci.yaml
code_quality/.flake8
code_quality/Makefile
code_quality/mypy.ini
code_quality/pylintrc
requirements/requirements.in
requirements/requirements.txt
requirements/test_requirements.in
requirements/test_requirements.txt
tests/Makefile
tests/__init__.py
tests/pytest.ini
tests/integration/__init__.py
tests/integration/test_integration.py
tests/load/__init__.py
tests/load/test_load.py
tests/regressions/__init__.py
tests/regressions/test_regressions.py
tests/unit/__init__.py
tests/unit/test_batch_processor.py
tests/unit/test_server.py
tests/unit/test_unit.py