Metadata-Version: 2.1
Name: octomy-batch
Version: 2.0.27
Summary: octomy/batch
Home-page: https://gitlab.com/octomy/batch
Author: OctoMY
Author-email: pypi@octomy.org
Maintainer: OctoMY
Maintainer-email: pypi@octomy.org
License: Proprietary Software License
Project-URL: Docs, https://gitlab.com/octomy/batch//-/blob/production/README.md
Project-URL: Bugs, https://gitlab.com/octomy/batch/issues
Project-URL: C.I., https://gitlab.com/octomy/batch/pipelines
Keywords: python3,batch,processing,async
Platform: Linux
Classifier: Development Status :: 1 - Planning
Classifier: Intended Audience :: Developers
Classifier: Intended Audience :: Information Technology
Classifier: Intended Audience :: Science/Research
Classifier: Intended Audience :: Other Audience
Classifier: Topic :: Utilities
Classifier: Natural Language :: English
Classifier: Operating System :: POSIX :: Linux
Classifier: Programming Language :: Python :: 3.9
Classifier: Topic :: Other/Nonlisted Topic
Requires-Python: >=3.9
License-File: ./LICENSE
